catgrad/__init__.py
catgrad/combinators.py
catgrad/compile.py
catgrad/layers.py
catgrad/signature.py
catgrad/bidirectional/functor.py
catgrad/bidirectional/operation.py
catgrad/core/__init__.py
catgrad/core/operation.py
catgrad/special/definition.py
catgrad/special/parameter.py
catgrad/target/__init__.py
catgrad/target/ast.py
catgrad/target/python/__init__.py
catgrad/target/python/special.py
catgrad/target/python/array_backend/__init__.py
catgrad/target/python/array_backend/numpy.py
catgrad/target/python/array_backend/torch.py
catgrad/target/python/array_backend/type.py
catgrad/target/python/codegen/__init__.py
catgrad/target/python/codegen/codegen.py
catgrad/target/python/codegen/definition.py
catgrad/target/python/codegen/operation.py
catgrad-0.2.2.dist-info/METADATA
catgrad-0.2.2.dist-info/WHEEL
catgrad-0.2.2.dist-info/licenses/LICENSE
catgrad-0.2.2.dist-info/RECORD
