Metadata-Version: 2.4
Name: catgrad
Version: 0.2.2
Summary: deep learning with reverse derivatives
Project-URL: Homepage, https://github.com/statusfailed/catgrad/
Project-URL: Github, https://github.com/statusfailed/catgrad/
Author-email: Paul Wilson <paul@statusfailed.com>
License-File: LICENSE
Classifier: License :: OSI Approved :: MIT License
Classifier: Programming Language :: Python :: 3
Requires-Python: >=3.8
Requires-Dist: numpy~=1.26.4
Requires-Dist: open-hypergraphs~=0.1.3
Provides-Extra: dev
Requires-Dist: hypothesis; extra == 'dev'
Requires-Dist: pytest; extra == 'dev'
Requires-Dist: scipy~=1.15.1; extra == 'dev'
